scGeneClust/__init__.py
scGeneClust/_model.py
scGeneClust/utils.py
scGeneClust/pp/__init__.py
scGeneClust/pp/decomposition.py
scGeneClust/pp/preprocessing.py
scGeneClust/tl/__init__.py
scGeneClust/tl/_utils.py
scGeneClust/tl/cluster.py
scGeneClust/tl/confidence.py
scGeneClust/tl/filtering.py
tests/__init__.py
tests/test_GeneClust.py
GeneClust-0.0.1.dist-info/LICENSE
GeneClust-0.0.1.dist-info/METADATA
GeneClust-0.0.1.dist-info/WHEEL
GeneClust-0.0.1.dist-info/top_level.txt
GeneClust-0.0.1.dist-info/RECORD
