Metadata-Version: 2.1
Name: GeneClust
Version: 0.0.1
Summary: Cofunctional grouping-based feature gene selection for unsupervised scRNA-seq clustering
Home-page: https://github.com/ToryDeng/scGeneClust
Author: Tao Deng
Author-email: taodeng@link.cuhk.edu.cn
License: GPL v3
Platform: UNKNOWN
Classifier: Programming Language :: Python :: 3
Classifier: License :: OSI Approved :: GNU General Public License v3 (GPLv3)
Classifier: Operating System :: OS Independent
Requires-Python: >=3.8
License-File: LICENSE
Requires-Dist: pandas (>=1.4.2)
Requires-Dist: anndata (>=0.8.0)
Requires-Dist: numpy (>=1.21.5)
Requires-Dist: loguru (>=0.6.0)
Requires-Dist: sklearn (>=0.0)
Requires-Dist: scikit-learn (>=1.1.1)
Requires-Dist: scanpy (>=1.9.1)
Requires-Dist: scipy (>=1.7.3)
Requires-Dist: leidenalg (>=0.8.9)
